noahs_tts/__init__.py
noahs_tts/tts.py
noahs_tts-0.1.2.dist-info/METADATA
noahs_tts-0.1.2.dist-info/WHEEL
noahs_tts-0.1.2.dist-info/top_level.txt
noahs_tts-0.1.2.dist-info/RECORD
