Metadata-Version: 2.4
Name: noahs_tts
Version: 0.1.2
Summary: A wrapper class to get started using Text To Speech quickly
Author-email: Noah Jones <jonesnoah45010@gmail.com>
License: MIT
Project-URL: Homepage, https://github.com/jonesnoah45010/noahs_tts
Requires-Python: >=3.9
Requires-Dist: pyttsx3
